prune_captcha/__init__.py
prune_captcha/utils.py
prune_captcha/static/prune_captcha/css/captcha.css
prune_captcha/static/prune_captcha/js/captcha.js
prune_captcha/templates/prune_captcha/captcha.html
prune_libs/__init__.py
prune_libs/commons/__init__.py
prune_libs/commons/base_model.py
prune_libs/commons/dates.py
prune_libs/commons/decorators.py
prune_libs/commons/email.py
prune_libs/commons/parse.py
prune_libs/commons/responses.py
prune_libs/commons/static_finder.py
prune_libs/commons/strings.py
prune_libs/logic/__init__.py
prune_libs/logic/cleaned_data.py
prune_libs/templatetags/__init__.py
prune_libs/templatetags/markdown_tags.py
prune_libs/templatetags/other.py
prune_libs/tests/__init__.py
prune_libs/tests/commons/__init__.py
prune_libs/tests/commons/test_dates.py
prune_libs/tests/commons/test_parse.py
prune_libs/tests/commons/test_strings.py
prune_libs/tests/logic/__init__.py
prune_libs/tests/logic/test_cleaned_data.py
prune_libs/tests/website/__init__.py
prune_libs/tests/website/test_contact.py
prune_libs/tests/website/test_utils.py
prune_libs/website/__init__.py
prune_libs/website/contact.py
prune_libs/website/utils.py
prune_libs-1.21.3.dist-info/METADATA
prune_libs-1.21.3.dist-info/WHEEL
prune_libs-1.21.3.dist-info/top_level.txt
prune_libs-1.21.3.dist-info/RECORD
