Metadata-Version: 2.4
Name: prune_libs
Version: 1.21.3
Summary: Python libraries for Prune.
Author-email: Arnout <bastien@prune.sh>
Project-URL: Made_by, https://prune.sh/
Keywords: captcha,django,code-quality
Classifier: Programming Language :: Python :: 3
Classifier: License :: OSI Approved :: MIT License
Classifier: Operating System :: OS Independent
Requires-Python: <4.0,>=3.12
Requires-Dist: django>=5.2
Requires-Dist: django-stubs>=5.2.0
Requires-Dist: pydantic>=2.11.3
Requires-Dist: pytest>=8.4.0
Requires-Dist: sendgrid>=6.11.0
Requires-Dist: ty>=0.0.1a8
